<?xml version="1.0"?>
<!DOCTYPE section PUBLIC "-//OASIS//DTD DocBook XML V4.5//EN" "http://www.oasis-open.org/docbook/xml/4.5/docbookx.dtd" [ <!ENTITY % entities SYSTEM "entities.ent"> %entities; ]>
<!-- Copyright FUJITSU LIMITED 2017 -->
<sect1>
 <title>Abbreviations</title>
 <para>
  This manual uses the following abbreviations:
 </para>

<!--<row>
                            <entry><b><ph conref="../product-name.xml#ProductNameTopic/Product_Abbr"/></b></entry>
                            <entry><ph conref="../../shared/product-name.xml#ProductNameTopic/Product_Name"/></entry>
                        </row>-->
    <formalpara>
     <title>IaaS</title>
     <para>Infrastructure as a Service</para>
    </formalpara>
    <formalpara>
     <title>ICMP</title>
     <para>Internet Control Message Protocol</para>
    </formalpara>
    <formalpara>
     <title>OS</title>
     <para>Operating System</para>
    </formalpara>
    <formalpara>
     <title>OSS</title>
     <para>Open Source Software</para>
    </formalpara>
    <formalpara>
     <title>PaaS</title>
     <para>Platform as a Service</para>
    </formalpara>
    <formalpara>
     <title>SaaS</title>
     <para>Software as a Service</para>
    </formalpara>

</sect1>
